poly_igdb/__init__.py
poly_igdb/igdbclient.py
poly_igdb/igdbgame.py
poly_igdb-0.1.11.dist-info/METADATA
poly_igdb-0.1.11.dist-info/WHEEL
poly_igdb-0.1.11.dist-info/top_level.txt
poly_igdb-0.1.11.dist-info/RECORD
